itreport/__init__.py
itreport/jiradump.py
itreport/reader.py
itreport/report.py
itreport/reporter.py
itreport/retriever.py
itreport/writer.py
jirareport/__init__.py
jirareport/__main__.py
jirareport/dump.py
jirareport/reader.py
jirareport/report.py
jirareport/reporter.py
jirareport/retriever.py
jirareport/writer.py
itreport-0.0.2.dist-info/METADATA
itreport-0.0.2.dist-info/WHEEL
itreport-0.0.2.dist-info/entry_points.txt
itreport-0.0.2.dist-info/top_level.txt
itreport-0.0.2.dist-info/RECORD
